indicators/__init__.py
indicators/base_indicator.py
indicators/deviationExpectation/__init__.py
indicators/deviationExpectation/close_minus_ma.py
indicators/informationContent/__init__.py
indicators/informationContent/entropy.py
indicators/informationContent/rangeIQR.py
indicators/trend/__init__.py
indicators/trend/adx.py
indicators/trend/aroon.py
indicators/trend/detrended_rsi.py
indicators/trend/macd.py
indicators/trend/mad.py
indicators/trend/polynomial_trend.py
indicators/trend/ppo.py
indicators/trend/price_int.py
indicators/trend/rsi_mod.py
indicators/trend/stochastic.py
indicators/trend/stochastic_rsi.py
indicators/volume/__init__.py
indicators/volume/vol_spread.py
indicatorPy-0.1.5.dist-info/METADATA
indicatorPy-0.1.5.dist-info/WHEEL
indicatorPy-0.1.5.dist-info/top_level.txt
indicatorPy-0.1.5.dist-info/RECORD
