Metadata-Version: 2.1
Name: indicatorPy
Version: 0.1.5
Summary: Yet Another Library for technical indicators, but this time with more stationarity.
Author-email: Mayank Khanna <cryptex.mk@gmail.com>
Project-URL: Homepage, https://github.com/monk-boop/indicatorPy
Project-URL: Bug Tracker, https://github.com/monk-boop/indicatorPy/issues
Classifier: Programming Language :: Python :: 3
Classifier: License :: OSI Approved :: MIT License
Classifier: Operating System :: OS Independent
Requires-Python: >=3.7
Requires-Dist: pandas
Requires-Dist: numpy
